setup.py
pepize/__init__.py
pepize.egg-info/PKG-INFO
pepize.egg-info/SOURCES.txt
pepize.egg-info/dependency_links.txt
pepize.egg-info/not-zip-safe
pepize.egg-info/requires.txt
pepize.egg-info/top_level.txt