Metadata-Version: 1.0
Name: pepize
Version: 0.1
Summary: Easier than refactoring
Home-page: http://github.com/Euphe/pepize
Author: Boris Tseitlin
Author-email: b.tseytlin@lambda-it.ru
License: MIT
Platform: UNKNOWN
